maser/tools/__init__.py
maser/tools/cdf/__init__.py
maser/tools/cdf/cdfcompare/__init__.py
maser/tools/cdf/cdfcompare/cdf_compare.py
maser/tools/cdf/cdfcompare/subparser.py
maser/tools/cdf/install.py
maser/tools/cdf/serializer/__init__.py
maser/tools/cdf/serializer/exceptions.py
maser/tools/cdf/serializer/globals.py
maser/tools/cdf/serializer/skeleton.py
maser/tools/cdf/serializer/skeletoncdf.py
maser/tools/cdf/serializer/skeletontable.py
maser/tools/cdf/serializer/subparser.py
maser/tools/cdf/serializer/test.py
maser/tools/cdf/serializer/txt.py
maser/tools/cdf/serializer/xlsx.py
maser/tools/cdf/tools.py
maser/tools/cdf/validator/__init__.py
maser/tools/cdf/validator/subparser.py
maser/tools/cdf/validator/validator.py
maser/tools/settings.py
maser/tools/support/cdf/converter_example.xlsx
maser/tools/support/cdf/skeleton.skt-tpl
maser/tools/support/cdf/validator_model_example.json
maser/tools/support/cdf/validator_model_istp.json
maser/tools/support/data/CDFLeapSeconds.txt
maser/tools/time/__init__.py
maser/tools/time/const.py
maser/tools/time/leapsec.py
maser/tools/time/subparser.py
maser/tools/time/test_time.py
maser/tools/time/time.py
maser/tools/toolbox.py
maser_tools-0.3.1.dist-info/METADATA
maser_tools-0.3.1.dist-info/WHEEL
maser_tools-0.3.1.dist-info/RECORD
