Metadata-Version: 2.3
Name: maser-tools
Version: 0.3.1
Summary: Tools to handle some file formats supported in maser-data package
Home-page: https://pypi.org/project/maser-tools
License: CECILL-B
Keywords: maser,data science,radioastronomy
Author: MASER team
Author-email: contact.maser@obspm.fr
Requires-Python: >=3.9,<4
Classifier: License :: CeCILL-B Free Software License Agreement (CECILL-B)
Classifier: Programming Language :: Python :: 3
Classifier: Programming Language :: Python :: 3.9
Classifier: Programming Language :: Python :: 3.10
Classifier: Programming Language :: Python :: 3.11
Classifier: Programming Language :: Python :: 3.12
Classifier: Programming Language :: Python :: 3.13
Requires-Dist: jinja2 (>=3.1.2,<4.0.0)
Requires-Dist: numpy (>=1.23,<2.0)
Requires-Dist: openpyxl (>=3.0.10,<4.0.0)
Requires-Dist: pytz (>=2022.4,<2023.0)
Requires-Dist: spacepy (>=0.5,<1.0)
Project-URL: Repository, https://github.com/maserlib/maser4py
